[
  {
    "src": "photos/IMG_5783.jpg",
    "name": "IMG_5783.jpg",
    "date": "2026-07-10"
  },
  {
    "src": "photos/IMG_5775.jpg",
    "name": "IMG_5775.jpg",
    "date": "2026-07-10"
  },
  {
    "src": "photos/99985.JPG",
    "name": "99985.JPG",
    "date": "2026-07-09"
  },
  {
    "src": "photos/IMG_5719.jpg",
    "name": "IMG_5719.jpg",
    "date": "2026-07-09"
  },
  {
    "src": "photos/IMG_5666.jpg",
    "name": "IMG_5666.jpg",
    "date": "2026-07-07"
  },
  {
    "src": "photos/C394FD2E-144D-4660-AE31-2666637C7269.PNG",
    "name": "C394FD2E-144D-4660-AE31-2666637C7269.PNG",
    "date": "2026-07-05"
  },
  {
    "src": "photos/IMG_5561.jpg",
    "name": "IMG_5561.jpg",
    "date": "2026-07-04"
  },
  {
    "src": "photos/IMG_5559.jpg",
    "name": "IMG_5559.jpg",
    "date": "2026-07-04"
  },
  {
    "src": "photos/livePhoto_1782910087.JPG",
    "name": "livePhoto_1782910087.JPG",
    "date": "2026-07-01"
  },
  {
    "src": "photos/IMG_5446.jpg",
    "name": "IMG_5446.jpg",
    "date": "2026-06-28"
  },
  {
    "src": "photos/IMG_5119.jpg",
    "name": "IMG_5119.jpg",
    "date": "2026-06-25"
  },
  {
    "src": "photos/IMG_7122.JPG",
    "name": "IMG_7122.JPG",
    "date": "2026-06-20"
  }
]